{
  "tickers": [
    { "symbol": "JWL.NS",        "name": "Jupiter Wagons",              "exchange": "NSE", "search_terms": ["Jupiter Wagons", "JWL"] },
    { "symbol": "TEXRAIL.NS",    "name": "Texmaco Rail",                "exchange": "NSE", "search_terms": ["Texmaco Rail", "Texmaco"] },
    { "symbol": "TITAGARH.NS",   "name": "Titagarh Rail Systems",       "exchange": "NSE", "search_terms": ["Titagarh Rail", "Titagarh"] },
    { "symbol": "AXISCADES.NS",  "name": "Axiscades Technologies",      "exchange": "NSE", "search_terms": ["Axiscades", "AXISCADES"] },
    { "symbol": "AVALON.NS",     "name": "Avalon Technologies",         "exchange": "NSE", "search_terms": ["Avalon Technologies"] },
    { "symbol": "RPTECH.NS",     "name": "Rashi Peripherals",           "exchange": "NSE", "search_terms": ["Rashi Peripherals", "RP Tech", "RPTECH"] },
    { "symbol": "COFORGE.NS",    "name": "Coforge",                     "exchange": "NSE", "search_terms": ["Coforge"] },
    { "symbol": "PERSISTENT.NS", "name": "Persistent Systems",          "exchange": "NSE", "search_terms": ["Persistent Systems"] },
    { "symbol": "REDTAPE.NS",    "name": "Red Tape",                    "exchange": "NSE", "search_terms": ["Red Tape", "Redtape"] },
    { "symbol": "ADINATH.NS",    "name": "Aditya Infotech",             "exchange": "NSE", "search_terms": ["Aditya Infotech"] },
    { "symbol": "CYIENTDLM.NS",  "name": "Cyient DLM",                  "exchange": "NSE", "search_terms": ["Cyient DLM"] },
    { "symbol": "DCXINDIA.NS",   "name": "DCX Systems",                 "exchange": "NSE", "search_terms": ["DCX Systems"] },
    { "symbol": "DIXON.NS",      "name": "Dixon Technologies",          "exchange": "NSE", "search_terms": ["Dixon Technologies", "Dixon"] },
    { "symbol": "QUADRANT.NS",   "name": "Quadrant Future Tek",         "exchange": "NSE", "search_terms": ["Quadrant Future Tek", "Quadrant Future"] },
    { "symbol": "TATATECH.NS",   "name": "Tata Technologies",           "exchange": "NSE", "search_terms": ["Tata Technologies"] },
    { "symbol": "TANEJAERO.BO",  "name": "Taneja Aerospace",            "exchange": "BSE", "search_terms": ["Taneja Aerospace", "TAAL"] },
    { "symbol": "E2E.NS",        "name": "E2E Networks",                "exchange": "NSE", "search_terms": ["E2E Networks"] },
    { "symbol": "EPACK.NS",      "name": "Epack Durable",               "exchange": "NSE", "search_terms": ["Epack Durable"] },
    { "symbol": "EMIL.NS",       "name": "Electronics Mart India",      "exchange": "NSE", "search_terms": ["Electronics Mart India", "Electronics Mart"] },
    { "symbol": "GRSE.NS",       "name": "Garden Reach Shipbuilders",   "exchange": "NSE", "search_terms": ["GRSE", "Garden Reach Shipbuilders"] },
    { "symbol": "IDEAFORGE.NS",  "name": "ideaForge Technology",        "exchange": "NSE", "search_terms": ["ideaForge", "Ideaforge"] },
    { "symbol": "IKIO.NS",       "name": "IKIO Technologies",           "exchange": "NSE", "search_terms": ["IKIO"] },
    { "symbol": "JSWINFRA.NS",   "name": "JSW Infrastructure",          "exchange": "NSE", "search_terms": ["JSW Infrastructure", "JSW Infra"] },
    { "symbol": "KPITTECH.NS",   "name": "KPIT Technologies",           "exchange": "NSE", "search_terms": ["KPIT Technologies", "KPIT Tech"] },
    { "symbol": "NAZARA.NS",     "name": "Nazara Technologies",         "exchange": "NSE", "search_terms": ["Nazara Technologies", "Nazara"] },
    { "symbol": "NETWEB.NS",     "name": "Netweb Technologies",         "exchange": "NSE", "search_terms": ["Netweb Technologies", "Netweb"] },
    { "symbol": "PGEL.NS",       "name": "PG Electroplast",             "exchange": "NSE", "search_terms": ["PG Electroplast"] },
    { "symbol": "REMSONS.NS",    "name": "Remsons Industries",          "exchange": "NSE", "search_terms": ["Remsons Industries", "Remsons"] },
    { "symbol": "SAKSOFT.NS",    "name": "Saksoft",                     "exchange": "NSE", "search_terms": ["Saksoft"] },
    { "symbol": "TVSSCS.NS",     "name": "TVS Supply Chain Solutions",  "exchange": "NSE", "search_terms": ["TVS Supply Chain", "TVSSCS"] },
    { "symbol": "UNIMECH.NS",    "name": "Unimech Aerospace",           "exchange": "NSE", "search_terms": ["Unimech Aerospace", "Unimech"] },
    { "symbol": "ZENTEC.NS",     "name": "Zen Technologies",            "exchange": "NSE", "search_terms": ["Zen Technologies"] }
  ]
}
